dcel/__init__.py
dcel/_base.py
dcel/_cache_invalidate.py
dcel/_cache_update.py
dcel/_cached.py
django_cache_expression_language-0.0.4.dist-info/LICENSE
django_cache_expression_language-0.0.4.dist-info/METADATA
django_cache_expression_language-0.0.4.dist-info/WHEEL
django_cache_expression_language-0.0.4.dist-info/top_level.txt
django_cache_expression_language-0.0.4.dist-info/RECORD
