Metadata-Version: 2.1
Name: django-cache-expression-language
Version: 0.0.4
Summary: Expression Language Cache Decorator for Django
Home-page: https://github.com/dadangeuy/dcel
Author: Irsyad Rizaldi
Author-email: irsyad.rizaldi97@gmail.com
License: UNKNOWN
Platform: UNKNOWN
Classifier: Programming Language :: Python :: 3
Classifier: License :: OSI Approved :: BSD License
Classifier: Operating System :: OS Independent
Classifier: Framework :: Django
Classifier: Environment :: Web Environment
Requires-Python: >=3
